{"width":512,"imagePath":"girl-fall_tex.png","height":256,"name":"girl-fall","SubTexture":[{"frameHeight":150,"y":111,"frameX":-24,"width":90,"frameY":-51,"height":87,"name":"7_fall_1","frameWidth":150,"x":271},{"frameHeight":150,"y":111,"frameX":-18,"width":90,"frameY":-78,"height":60,"name":"7_fall_6","frameWidth":150,"x":363},{"frameHeight":150,"y":1,"frameX":-18,"width":90,"frameY":-27,"height":111,"name":"7_fall_4","frameWidth":150,"x":1},{"frameHeight":150,"y":1,"frameX":-18,"width":90,"frameY":-30,"height":108,"name":"7_fall_3","frameWidth":150,"x":93},{"frameHeight":150,"y":111,"frameX":-27,"width":90,"frameY":-48,"height":90,"name":"7_fall_0","frameWidth":150,"x":179},{"frameHeight":150,"y":111,"frameX":-24,"width":84,"frameY":-33,"height":105,"name":"7_fall_2","frameWidth":150,"x":93},{"frameHeight":150,"y":114,"frameX":-18,"width":90,"frameY":-27,"height":111,"name":"7_fall_5","frameWidth":150,"x":1}]}